{
  "results": [
    {
      "url": "https://www.marktechpost.com/",
      "status": "available",
      "main_feed_url": "https://www.marktechpost.com/feed",
      "ai_feed_url": "https://www.marktechpost.com/category/artificial-intelligence/feed/",
      "tech_feed_url": null,
      "science_feed_url": null,
      "directory_page_url": null,
      "is_ai_focused": false,
      "recommended_feed": "ai_feed_url",
      "recommended_feed_url": "https://www.marktechpost.com/category/artificial-intelligence/feed/",
      "method": "preset",
      "notes": "Found at /feed",
      "has_full_content": true,
      "http_fetch_works": null,
      "main_feed_latest_date": "2026-01-07",
      "ai_feed_latest_date": "2026-01-07",
      "fallback_reason": null
    },
    {
      "url": "https://www.byhand.ai/",
      "status": "available",
      "main_feed_url": "https://www.byhand.ai/feed",
      "ai_feed_url": null,
      "tech_feed_url": null,
      "science_feed_url": null,
      "directory_page_url": null,
      "is_ai_focused": false,
      "recommended_feed": "main_feed_url",
      "recommended_feed_url": "https://www.byhand.ai/feed",
      "method": "preset",
      "notes": "Found at /feed",
      "has_full_content": true,
      "http_fetch_works": null,
      "main_feed_latest_date": "2026-01-01",
      "ai_feed_latest_date": null,
      "fallback_reason": null
    },
    {
      "url": "https://news.hada.io/new",
      "status": "available",
      "main_feed_url": "https://news.hada.io/rss/news",
      "ai_feed_url": null,
      "tech_feed_url": null,
      "science_feed_url": null,
      "directory_page_url": null,
      "is_ai_focused": false,
      "recommended_feed": "main_feed_url",
      "recommended_feed_url": "https://news.hada.io/rss/news",
      "method": "agent_browse",
      "notes": "Found RSS feed URL in the website's HTML. The feed appears to be publicly accessible at /rss/news path.",
      "has_full_content": false,
      "http_fetch_works": null,
      "main_feed_latest_date": null,
      "ai_feed_latest_date": null,
      "fallback_reason": null
    }
  ],
  "timestamp": "2026-01-08T04:55:47.969774",
  "total": 3,
  "available": 3,
  "paywalled": 0,
  "unavailable": 0,
  "ai_focused": 0,
  "has_ai_category": 1,
  "has_tech_feed": 0,
  "has_science_feed": 0,
  "with_full_content": 2,
  "with_http_fetch": 0,
  "no_content_access": 1
}